pytimer/__init__.py
pytimer/pytimer.py
pytimer/static.py
pytimer-0.0.16.dist-info/LICENSE
pytimer-0.0.16.dist-info/METADATA
pytimer-0.0.16.dist-info/WHEEL
pytimer-0.0.16.dist-info/top_level.txt
pytimer-0.0.16.dist-info/RECORD
